setup.py
ifa/__init__.py
ifa/__main__.py
ifa/ifa_runner.py
ifa/message_processor/__init__.py
ifa/message_processor/message_parser.py
ifa/message_processor/nlp/__init__.py
ifa/message_processor/nlp/keyword_parser.py
ifa/message_processor/nlp/qabot.py
ifa/message_processor/wechat/__init__.py
ifa/message_processor/wechat/message_processor.py
ifa/message_processor/wxwork/__init__.py
ifa/message_processor/wxwork/message_processor.py
ifa/message_receiver/__init__.py
ifa/message_receiver/wechat/__init__.py
ifa/message_receiver/wechat/message_receiver.py
ifa/message_receiver/wxwork/__init__.py
ifa/message_receiver/wxwork/message_receiver.py
ifa/message_sender/__init__.py
ifa/message_sender/wechat/__init__.py
ifa/message_sender/wechat/image_message_sender.py
ifa/message_sender/wechat/message_sender.py
ifa/message_sender/wechat/text_message_sender.py
ifa/message_sender/wxwork/__init__.py
ifa/message_sender/wxwork/image_message_sender.py
ifa/message_sender/wxwork/message_sender.py
ifa/message_sender/wxwork/text_message_sender.py
ifa/util/__init__.py
ifa/util/config.py
ifa/util/struct.py
ifa/util/wx_crypto/WXBizMsgCrypt3.py
ifa/util/wx_crypto/__init__.py
ifa/util/wx_crypto/ierror.py
surfing/__init__.py
surfing/__main__.py
surfing/_version.py
surfing/aws_util.py
surfing/constant.py
surfing/match_engine.py
surfing/structure.py
surfing.egg-info/PKG-INFO
surfing.egg-info/SOURCES.txt
surfing.egg-info/dependency_links.txt
surfing.egg-info/requires.txt
surfing.egg-info/top_level.txt
surfing/data/__init__.py
surfing/data/constant.py
surfing/data/struct.py
surfing/data/api/__init__.py
surfing/data/api/basic.py
surfing/data/api/derived.py
surfing/data/api/fof_api.py
surfing/data/api/portfolio.py
surfing/data/api/raw.py
surfing/data/api/raw_tl.py
surfing/data/api/research_api.py
surfing/data/api/research_tool.py
surfing/data/api/test_api.py
surfing/data/api/view.py
surfing/data/fund/__init__.py
surfing/data/fund/basic/__init__.py
surfing/data/fund/basic/barra_cne5_factor_data.py
surfing/data/fund/basic/basic_data_helper.py
surfing/data/fund/basic/basic_data_part1.py
surfing/data/fund/basic/basic_data_part2_fund_ret.py
