Metadata-Version: 1.0
Name: surfing
Version: 0.4.98
Summary: backtest engine
Home-page: UNKNOWN
Author: puyuantech
Author-email: info@puyuan.tech
License: UNKNOWN
Platform: UNKNOWN
